hexahexacontadecimal/__init__.py
hexahexacontadecimal/num_encode_base64.py
hexahexacontadecimal-2.2.1.dist-info/METADATA
hexahexacontadecimal-2.2.1.dist-info/RECORD
hexahexacontadecimal-2.2.1.dist-info/WHEEL
hexahexacontadecimal-2.2.1.dist-info/top_level.txt
