Metadata-Version: 2.1
Name: hexahexacontadecimal
Version: 2.2.1
Summary: The best way to express a number in a URL.
Home-page: https://github.com/aljungberg/hexahexacontadecimal
Author: Alexander Ljungberg
Author-email: aljungberg@slevenbits.com
License: UNKNOWN
Keywords: base64,hexahexacontadecimal,hhc,base66,url
Platform: UNKNOWN
Classifier: Programming Language :: Python
Classifier: Development Status :: 5 - Production/Stable
Classifier: Intended Audience :: Developers
Classifier: Topic :: Software Development :: Libraries
Classifier: License :: OSI Approved :: BSD License
Classifier: Operating System :: POSIX
